setup.py
common/__init__.py
common/baserequest.py
common/baseresponse.py
common/sendrequest.py
tool/__init__.py
tool/config.py
tool/jsonpath_tool.py
tool/key_driver.py
tool/key_map.py
tool/key_tools.py
tool/log.py
tool/tools.py
xiaoheauto.egg-info/PKG-INFO
xiaoheauto.egg-info/SOURCES.txt
xiaoheauto.egg-info/dependency_links.txt
xiaoheauto.egg-info/requires.txt
xiaoheauto.egg-info/top_level.txt